extratools_cloud/__init__.py
extratools_cloud/aws/__init__.py
extratools_cloud/aws/cloud_control.py
extratools_cloud/aws/helpers.py
extratools_cloud/aws/lambda_.py
extratools_cloud/aws/secrets_manager.py
extratools_cloud/aws/sqs.py
extratools_cloud/common/__init__.py
extratools_cloud/common/router.py
extratools_cloud/github/__init__.py
extratools_cloud/github/user.py
extratools_cloud/py.typed
extratools_cloud-0.1.12.dist-info/WHEEL
extratools_cloud-0.1.12.dist-info/METADATA
extratools_cloud-0.1.12.dist-info/RECORD
