Metadata-Version: 2.4
Name: extratools-cloud
Version: 0.1.12
Summary: 
Author: Chuancong Gao
Author-email: Chuancong Gao <chuanconggao@users.noreply.github.com>
License-Expression: MIT
Requires-Dist: extratools-core>=0.1.26
Requires-Dist: toolz>=1.0.0
Requires-Dist: boto3>=1.38.34 ; extra == 'aws'
Requires-Dist: cachetools>=6.1.0 ; extra == 'github'
Requires-Dist: httpx>=0.28.1 ; extra == 'github'
Requires-Python: >=3.12
Project-URL: Repository, https://github.com/chuanconggao/extratools-cloud
Provides-Extra: aws
Provides-Extra: github
